envswitch/__init__.py
envswitch/cli.py
envswitch/env_api.py
envswitch/env_api_linuximpl.py
envswitch/env_api_winimpl.py
envswitch/env_config.py
envswitch/gui.py
envswitch/qt_design.py
envswitch/utils.py
envswitch/yaml_ordered_dict.py
envswitch/resources/envswitch.ico
envswitch/resources/envswitch.png
envswitch-1.4.1.dist-info/DESCRIPTION.rst
envswitch-1.4.1.dist-info/METADATA
envswitch-1.4.1.dist-info/RECORD
envswitch-1.4.1.dist-info/WHEEL
envswitch-1.4.1.dist-info/entry_points.txt
envswitch-1.4.1.dist-info/metadata.json
envswitch-1.4.1.dist-info/top_level.txt
