Metadata-Version: 2.0
Name: envswitch
Version: 1.4.1
Summary: A very simple GUI and CLI to manage environment variables.
Home-page: https://github.com/smarie/env-switcher-gui
Author: Sylvain Marié
Author-email: sylvain.marie@schneider-electric.com
License: BSD 3-Clause
Download-URL: https://github.com/smarie/env-switcher-gui/tarball/1.4.1
Keywords: env-variable environment variable http proxy switch gui cli desktop application
Platform: UNKNOWN
Classifier: Development Status :: 4 - Beta
Classifier: Intended Audience :: Developers
Classifier: Topic :: Desktop Environment
Classifier: License :: OSI Approved :: BSD License
Classifier: Programming Language :: Python :: 3.5
Classifier: Programming Language :: Python :: 3.6
Requires-Dist: autoclass
Requires-Dist: click
Requires-Dist: pyyaml
